{
  "residents": [
    {
      "name": "devinroche",
      "id": "123456",
      "dob": "01/29/1996",
      "age":21,
      "tmpName": "fart face",
      "tmpDob": "",
      "tmpAge": 0
    },
    {
      "name": "Sue",
      "dob": "08/21/1978",
      "age":21,
      "id": "121456",
      "tmpName": "",
      "tmpDob": "",
      "tmpAge": 0
    },
    {
      "name": "Nate",
      "dob": "11/04/1960",
      "age":21,
      "id": "126446",
      "tmpName": "",
      "tmpDob": "",
      "tmpAge": 0
    }
  ]
}
